<annotation>
	<folder>JPEGImages</folder>
	<filename>data_hj_3183.jpg</filename>
	<path>E:\yolov5-slimming\VOCdevkit\VOC2007\JPEGImages\data_hj_3183.jpg</path>
	<source>
		<database>Unknown</database>
	</source>
	<size>
		<width>1280</width>
		<height>720</height>
		<depth>3</depth>
	</size>
	<segmented>0</segmented>
	<object>
		<name>plank</name>
		<pose>Unspecified</pose>
		<truncated>0</truncated>
		<difficult>0</difficult>
		<bndbox>
			<xmin>657</xmin>
			<ymin>423</ymin>
			<xmax>875</xmax>
			<ymax>638</ymax>
		</bndbox>
	</object>
	<object>
		<name>helmet</name>
		<pose>Unspecified</pose>
		<truncated>0</truncated>
		<difficult>0</difficult>
		<bndbox>
			<xmin>223</xmin>
			<ymin>170</ymin>
			<xmax>312</xmax>
			<ymax>246</ymax>
		</bndbox>
	</object>
	<object>
		<name>armband</name>
		<pose>Unspecified</pose>
		<truncated>0</truncated>
		<difficult>0</difficult>
		<bndbox>
			<xmin>216</xmin>
			<ymin>357</ymin>
			<xmax>270</xmax>
			<ymax>413</ymax>
		</bndbox>
	</object>
	<object>
		<name>face shield</name>
		<pose>Unspecified</pose>
		<truncated>0</truncated>
		<difficult>0</difficult>
		<bndbox>
			<xmin>858</xmin>
			<ymin>219</ymin>
			<xmax>947</xmax>
			<ymax>324</ymax>
		</bndbox>
	</object>
	<object>
		<name>extinguisher</name>
		<pose>Unspecified</pose>
		<truncated>0</truncated>
		<difficult>0</difficult>
		<bndbox>
			<xmin>560</xmin>
			<ymin>509</ymin>
			<xmax>617</xmax>
			<ymax>642</ymax>
		</bndbox>
	</object>
	<object>
		<name>fire sandbox</name>
		<pose>Unspecified</pose>
		<truncated>0</truncated>
		<difficult>0</difficult>
		<bndbox>
			<xmin>306</xmin>
			<ymin>536</ymin>
			<xmax>438</xmax>
			<ymax>665</ymax>
		</bndbox>
	</object>
	<object>
		<name>welding gloves</name>
		<pose>Unspecified</pose>
		<truncated>0</truncated>
		<difficult>0</difficult>
		<bndbox>
			<xmin>819</xmin>
			<ymin>385</ymin>
			<xmax>858</xmax>
			<ymax>464</ymax>
		</bndbox>
	</object>
	<object>
		<name>welding gloves</name>
		<pose>Unspecified</pose>
		<truncated>0</truncated>
		<difficult>0</difficult>
		<bndbox>
			<xmin>955</xmin>
			<ymin>375</ymin>
			<xmax>994</xmax>
			<ymax>450</ymax>
		</bndbox>
	</object>
	<object>
		<name>people</name>
		<pose>Unspecified</pose>
		<truncated>0</truncated>
		<difficult>0</difficult>
		<bndbox>
			<xmin>197</xmin>
			<ymin>175</ymin>
			<xmax>329</xmax>
			<ymax>710</ymax>
		</bndbox>
	</object>
	<object>
		<name>people</name>
		<pose>Unspecified</pose>
		<truncated>0</truncated>
		<difficult>0</difficult>
		<bndbox>
			<xmin>818</xmin>
			<ymin>220</ymin>
			<xmax>994</xmax>
			<ymax>612</ymax>
		</bndbox>
	</object>
</annotation>
